CountryInformation/CacheForCountries.py
CountryInformation/CacheForLanguages.py
CountryInformation/Country.py
CountryInformation/CountryData.py
CountryInformation/CountryInformationCore.py
CountryInformation/CountryUtilities.py
CountryInformation/CulturedLanguage.py
CountryInformation/Language.py
CountryInformation/LanguageCodeConversionUtilities.py
CountryInformation/LanguageData.py
CountryInformation/LanguageUtilities.py
CountryInformation/__init__.py
countryinformation-1.0.11.dist-info/METADATA
countryinformation-1.0.11.dist-info/WHEEL
countryinformation-1.0.11.dist-info/top_level.txt
countryinformation-1.0.11.dist-info/RECORD
