Metadata-Version: 2.4
Name: CountryInformation
Version: 1.0.11
Summary: CountryInformation is a project to provide certain country- and language-information in a way which is well processable programmatically.
Home-page: https://github.com/anionDev/CountryInformation
Author: Marius Göcke
Author-email: marius.goecke@gmail.com
Project-URL: Documentation, https://aniondev.github.io/CountryInformationReference/index.html
Project-URL: Changelog, https://github.com/anionDev/CountryInformation/tree/main/Other/Resources/Changelog
Keywords: package release build management
Classifier: Intended Audience :: Developers
Classifier: Topic :: Software Development :: Libraries :: Python Modules
Classifier: Programming Language :: Python :: 3.10
Classifier: License :: OSI Approved :: GNU General Public License v3 (GPLv3)
Classifier: Operating System :: POSIX :: Linux
Classifier: Operating System :: Microsoft :: Windows :: Windows 10
Classifier: Topic :: System :: Logging
Classifier: Topic :: System :: Monitoring
Classifier: Topic :: System :: Archiving :: Packaging
Classifier: Topic :: System :: Systems Administration
Classifier: Topic :: Terminals
Classifier: Topic :: Utilities
Requires-Python: >=3.10
Requires-Dist: ScriptCollection>=4.2.9
